dwdj/__init__.py
dwdj/cache.py
dwdj/context_processors.py
dwdj/date.py
dwdj/discover_providers.py
dwdj/fields.py
dwdj/http.py
dwdj/log.py
dwdj/middleware.py
dwdj/models.py
dwdj/shortcuts.py
dwdj/strutil.py
dwdj/testing.py
dwdj/transaction.py
dwdj/urls.py
dwdj/utils.py
dwdj/views.py
dwdj/management/__init__.py
dwdj/management/base.py
dwdj/management/commands/__init__.py
dwdj/management/commands/checkmigrations.py
dwdj/management/commands/dump_app_data.py
dwdj/management/commands/script.py
dwdj/templatetags/__init__.py
dwdj/templatetags/human_size.py
dwdj/templatetags/localdt.py
dwdj/templatetags/mkrange.py
dwdj/templatetags/plural.py
dwdj/templatetags/static_link.py
dwdj/templatetags/txt2html.py
dwdj/templatetags/tests/__init__.py
dwdj/templatetags/tests/test_localdt.py
dwdj/tests/__init__.py
dwdj/tests/test_discover.py
dwdj/tests/test_mail.py
dwdj/tests/test_transaction.py
dwdj/tests/test_urls.py
dwdj-0.9.7.dist-info/DESCRIPTION.rst
dwdj-0.9.7.dist-info/METADATA
dwdj-0.9.7.dist-info/RECORD
dwdj-0.9.7.dist-info/WHEEL
dwdj-0.9.7.dist-info/metadata.json
dwdj-0.9.7.dist-info/pbr.json
dwdj-0.9.7.dist-info/top_level.txt
