Metadata-Version: 2.0
Name: dwdj
Version: 0.9.7
Summary: A collection of useful django utilities.
Home-page: https://github.com/wolever/dwdj
Author: David Wolever
Author-email: david@wolever.net
License: BSD
Platform: UNKNOWN
Classifier: Development Status :: 4 - Beta
Classifier: Intended Audience :: Developers
Classifier: License :: OSI Approved :: BSD License
Classifier: Natural Language :: English
Classifier: Operating System :: OS Independent
Classifier: Programming Language :: Python
Classifier: Topic :: Utilities
